make4db_snowflake.py
make4db_snowflake-0.1.2.dist-info/METADATA
make4db_snowflake-0.1.2.dist-info/WHEEL
make4db_snowflake-0.1.2.dist-info/top_level.txt
make4db_snowflake-0.1.2.dist-info/RECORD
